{
  "url": "https://possibleminds.in/blog",
  "title": "Blog & Insights | Possible Minds",
  "content": "Blog & Insights | Possible Minds Latest Insights Explore our latest thoughts on AI, machine learning, and digital transformation AI Strategy The Real Reason AI Evals Matter for Your Business Beyond accuracy metrics: why AI evaluations are your competitive advantage and the key to responsible AI deployment that actually drives business value. Pranav Modi Aug 17, 2024 7 min read AI & Automation Why AI is the Future of Sales and Support AI is no longer a shiny sidekick; it's already outperforming human reps in speed, accuracy, and customer satisfaction. Here's why—and how PossibleMinds Supportbot makes it painless. PossibleMinds Team May 15, 2024 6 min read AI Trends Future of AI in Enterprise Discover how artificial intelligence is reshaping enterprise operations and decision-making processes in 2024 and beyond. PossibleMinds Team Mar 15, 2024 5 min read Case Study Precise MRI How artificial intelligence is revolutionizing MRI analysis and improving diagnostic accuracy in medical imaging. PossibleMinds Team Mar 10, 2024 6 min read Stay Updated with AI Trends Subscribe to our newsletter for the latest insights and updates in AI technology Subscribe Now Contact Us",
  "markdown": "\n\n##  Latest Insights \n\nExplore our latest thoughts on AI, machine learning, and digital transformation \n\nAI Strategy \n\n##  [ The Real Reason AI Evals Matter for Your Business ](/blog/the-real-reason-ai-evals-matter-for-your-business)\n\nBeyond accuracy metrics: why AI evaluations are your competitive advantage and the key to responsible AI deployment that actually drives business value. \n\nPranav Modi\n\nAug 17, 2024\n\n7 min read\n\nAI & Automation \n\n##  [ Why AI is the Future of Sales and Support ](/blog/why-ai-is-the-future-of-sales-and-support)\n\nAI is no longer a shiny sidekick; it's already outperforming human reps in speed, accuracy, and customer satisfaction. Here's why—and how PossibleMinds Supportbot makes it painless. \n\nPossibleMinds Team\n\nMay 15, 2024\n\n6 min read\n\nAI Trends \n\n##  [ Future of AI in Enterprise ](/blog/future-of-ai-in-enterprise)\n\nDiscover how artificial intelligence is reshaping enterprise operations and decision-making processes in 2024 and beyond. \n\nPossibleMinds Team\n\nMar 15, 2024\n\n5 min read\n\nCase Study \n\n##  [ Precise MRI ](/blog/precise-mri)\n\nHow artificial intelligence is revolutionizing MRI analysis and improving diagnostic accuracy in medical imaging. \n\nPossibleMinds Team\n\nMar 10, 2024\n\n6 min read\n\n##  Stay Updated with AI Trends \n\nSubscribe to our newsletter for the latest insights and updates in AI technology \n\n[ Subscribe Now ](/contact#newsletter) [ Contact Us ](/contact)\n",
  "links": [
    {
      "href": "https://possibleminds.in/",
      "text": "Possible Minds",
      "title": ""
    },
    {
      "href": "https://possibleminds.in/",
      "text": "Home",
      "title": ""
    },
    {
      "href": "https://possibleminds.in/#features",
      "text": "Features",
      "title": ""
    },
    {
      "href": "https://possibleminds.in/#pricing",
      "text": "Pricing",
      "title": ""
    },
    {
      "href": "https://possibleminds.in/reports",
      "text": "Reports",
      "title": ""
    },
    {
      "href": "https://possibleminds.in/#blog",
      "text": "Blog",
      "title": ""
    },
    {
      "href": "https://possibleminds.in/contact",
      "text": "Contact",
      "title": ""
    },
    {
      "href": "https://possibleminds.in/agent-readiness-audit",
      "text": "Agent Readiness Audit",
      "title": ""
    },
    {
      "href": "https://possibleminds.in/ai-preflight-checklist",
      "text": "AI Pre-Flight Checklist",
      "title": ""
    },
    {
      "href": "https://possibleminds.in/blog/the-real-reason-ai-evals-matter-for-your-business",
      "text": "The Real Reason AI Evals Matter for Your Business",
      "title": ""
    },
    {
      "href": "https://possibleminds.in/blog/why-ai-is-the-future-of-sales-and-support",
      "text": "Why AI is the Future of Sales and Support",
      "title": ""
    },
    {
      "href": "https://possibleminds.in/blog/future-of-ai-in-enterprise",
      "text": "Future of AI in Enterprise",
      "title": ""
    },
    {
      "href": "https://possibleminds.in/blog/precise-mri",
      "text": "Precise MRI",
      "title": ""
    },
    {
      "href": "https://possibleminds.in/contact#newsletter",
      "text": "Subscribe Now",
      "title": ""
    },
    {
      "href": "https://possibleminds.in/contact",
      "text": "Contact Us",
      "title": ""
    },
    {
      "href": "https://possibleminds.in/services",
      "text": "Services",
      "title": ""
    },
    {
      "href": "https://possibleminds.in/about",
      "text": "About Us",
      "title": ""
    },
    {
      "href": "https://possibleminds.in/blog",
      "text": "Blog",
      "title": ""
    },
    {
      "href": "https://possibleminds.in/contact",
      "text": "Contact",
      "title": ""
    },
    {
      "href": "https://possibleminds.in/services#consulting",
      "text": "AI Consulting",
      "title": ""
    },
    {
      "href": "https://possibleminds.in/services#implementation",
      "text": "Implementation",
      "title": ""
    },
    {
      "href": "https://possibleminds.in/services#training",
      "text": "Training",
      "title": ""
    },
    {
      "href": "https://possibleminds.in/services#support",
      "text": "Support",
      "title": ""
    }
  ],
  "metadata": {
    "scraped_at": "2025-09-18T11:31:54.330238",
    "status_code": 200,
    "content_type": "text/html",
    "content_length": 1180,
    "links_found": 23
  }
}